README.md
setup.py
bin/scenethesize
dagtasets/__init__.py
dagtasets/siamese.py
dagtasets/wi2013.py
dagtasets.egg-info/PKG-INFO
dagtasets.egg-info/SOURCES.txt
dagtasets.egg-info/dependency_links.txt
dagtasets.egg-info/requires.txt
dagtasets.egg-info/top_level.txt
lm_util/__init__.py
lm_util/argv.py
lm_util/colored_strings.py
lm_util/corpora.py
lm_util/encoder.py
scenethecizer/__init__.py
scenethecizer/synthecizer.py
scenethecizer/data/backgrounds/paper_texture.jpg
scenethecizer/data/corpora/01_the_ugly_duckling.txt