Metadata-Version: 1.0
Name: dagtasets
Version: 0.1.2.dev0
Summary: UNKNOWN
Home-page: https://github.com/anguelos/dagtasets
Author: Anguelos Nicolaou
Author-email: anguelos.nicolaou@gmail.com
License: Creative Commons Attribution-Noncommercial-Share Alike license
Platform: UNKNOWN
